ichec_django_core/__init__.py
ichec_django_core/admin.py
ichec_django_core/apps.py
ichec_django_core/settings.py
ichec_django_core/urls.py
ichec_django_core/migrations/0001_initial.py
ichec_django_core/migrations/0002_memberidentifier.py
ichec_django_core/migrations/0003_alter_formfieldvalue_value.py
ichec_django_core/migrations/0004_alter_member_profile_alter_member_profile_thumbnail.py
ichec_django_core/migrations/__init__.py
ichec_django_core/models/__init__.py
ichec_django_core/models/feedback.py
ichec_django_core/models/form.py
ichec_django_core/models/member.py
ichec_django_core/models/organization.py
ichec_django_core/models/utils.py
ichec_django_core/serializers/__init__.py
ichec_django_core/serializers/core.py
ichec_django_core/serializers/feedback.py
ichec_django_core/serializers/form.py
ichec_django_core/serializers/member.py
ichec_django_core/serializers/organization.py
ichec_django_core/utils/__init__.py
ichec_django_core/utils/authentication.py
ichec_django_core/utils/logger_middleware.py
ichec_django_core/utils/test_utils/__init__.py
ichec_django_core/utils/test_utils/models.py
ichec_django_core/utils/test_utils/portal_client.py
ichec_django_core/utils/test_utils/resources.py
ichec_django_core/utils/test_utils/rest_client.py
ichec_django_core/utils/test_utils/test_client.py
ichec_django_core/view_sets/__init__.py
ichec_django_core/view_sets/core.py
ichec_django_core/view_sets/feedback.py
ichec_django_core/view_sets/files.py
ichec_django_core/view_sets/form.py
ichec_django_core/view_sets/member.py
ichec_django_core/view_sets/organization.py
ichec_django_core/view_sets/pagination.py
ichec_django_core/view_sets/permissions.py
ichec_django_core-0.1.2.dist-info/licenses/LICENSE
ichec_django_core-0.1.2.dist-info/METADATA
ichec_django_core-0.1.2.dist-info/WHEEL
ichec_django_core-0.1.2.dist-info/top_level.txt
ichec_django_core-0.1.2.dist-info/RECORD
