Metadata-Version: 2.4
Name: ichec_django_core
Version: 0.1.2
Summary: Library of base Django app building blocks and utilities.
Author-email: Irish Centre for High End Computing <platformengineering@ichec.ie>
Project-URL: Repository, https://git.ichec.ie/platform-engineering/ichec-django-core
Project-URL: Homepage, https://git.ichec.ie/platform-engineering/ichec-django-core
Keywords: Web Application,Django
Classifier: Development Status :: 3 - Alpha
Classifier: Programming Language :: Python :: 3
Classifier: Operating System :: OS Independent
Requires-Python: >=3.10
License-File: LICENSE
Requires-Dist: django
Requires-Dist: markdown
Requires-Dist: pillow
Requires-Dist: pyyaml
Requires-Dist: pydantic
Requires-Dist: djangorestframework
Requires-Dist: django-filter
Requires-Dist: django-countries
Requires-Dist: django-cors-headers
Requires-Dist: django-downloadview
Requires-Dist: django-prometheus
Requires-Dist: mozilla-django-oidc
Provides-Extra: test
Requires-Dist: pytest; extra == "test"
Requires-Dist: pytest-cov; extra == "test"
Requires-Dist: pytest-sugar; extra == "test"
Requires-Dist: beautifulsoup4; extra == "test"
Requires-Dist: black; extra == "test"
Requires-Dist: flake8; extra == "test"
Requires-Dist: pylint; extra == "test"
Requires-Dist: mypy; extra == "test"
Requires-Dist: requests; extra == "test"
Requires-Dist: types-requests; extra == "test"
Requires-Dist: faker; extra == "test"
Requires-Dist: faker-file[docx,images,pdf]; extra == "test"
Provides-Extra: container
Requires-Dist: psycopg2-binary; extra == "container"
Requires-Dist: gunicorn; extra == "container"
Provides-Extra: types
Requires-Dist: types-requests; extra == "types"
Dynamic: license-file
